{
   "info":"success",
   "num":2,
   "result":[
      {
         "id":1,
         "judule":"Kirby Addon",
         "icone":"https://livemovies.club/mcpe_icons/kirby_addon.jpg",
         "file_url":"https://livemovies.club/mcpe_addons/kirby_addon.zip",
         "typeMCPE":"Addon",
         "html_file":"https://livemovies.club/mcpe_html/kirby_addon.html",
         "extension":"mcaddon",
         "deskripsine":"With this add-on add to your Minecraft world the character of Kirby Minecraft version taken from Super Smash Bros Ultimate, so you can get it as a pet or have it as a skin and includes sounds.\n\n"
      },
      {
         "id":2,
         "judule":"Super Mario Skins",
         "icone":"https://livemovies.club/mcpe_icons/super_mario_skins.jpg",
         "file_url":"https://livemovies.club/mcpe_skins/super_mario_skins.zip",
         "typeMCPE":"Skins",
         "html_file":"https://livemovies.club/mcpe_html/super_mario_skins.html",
         "extension":"mcpack",
         "deskripsine":"Hello!\nIts a me Mario!\nDo you like Super Mario bros?\nwith this skin pack you can enter to Mario world by being Mario and Luigi and even Peach!This skin pack contains 21 skins!Skins created by: PepeSupremoMx"
      }
   ]
}